cleansipy-0.1.13.dist-info/licenses/LICENSE
cleansipy-0.1.13.dist-info/licenses/LICENSE.txt.bak
puripy/__init__.py
puripy/__main__.py
puripy/app.py
puripy/categoricaldata.py
puripy/config.py
puripy/config_generator.py
puripy/dt.py
puripy/logo.py
puripy/maincat.py
puripy/maindt.py
puripy/mainnum.py
puripy/maintext.py
puripy/numericdata.py
puripy/textcleaner.py
cleansipy-0.1.13.dist-info/METADATA
cleansipy-0.1.13.dist-info/WHEEL
cleansipy-0.1.13.dist-info/entry_points.txt
cleansipy-0.1.13.dist-info/top_level.txt
cleansipy-0.1.13.dist-info/RECORD
